anarticle/__init__.py
anarticle/apps.py
anarticle/mixins.py
anarticle/models.py
anarticle/resolvers.py
anarticle/tests.py
anarticle/utils.py
anarticle/graphqls/__init__.py
anarticle/graphqls/article.graphql
anarticle/graphqls/bindables.py
anarticle/graphqls/bindables_sync.py
anarticle/graphqls/category.graphql
anarticle/graphqls/tag.graphql
anarticle/graphqls/type_defs.py
anarticle/migrations/0001_initial.py
anarticle/migrations/__init__.py
tests/__init__.py
tests/conftest.py
tests/test_resolvers.py
django_anarticle-0.1.0rc3.dist-info/LICENSE
django_anarticle-0.1.0rc3.dist-info/METADATA
django_anarticle-0.1.0rc3.dist-info/WHEEL
django_anarticle-0.1.0rc3.dist-info/top_level.txt
django_anarticle-0.1.0rc3.dist-info/RECORD
