Metadata-Version: 2.1
Name: django-anarticle
Version: 0.1.0rc3
Summary: App for publishing articles with tags and categories
Author-email: Chiu <chiutung.chen@aglean.com>
Project-URL: Homepage, https://github.com/aglean/django-anarticle
Keywords: django,graphql,ariadne,aglean,article,tag,category
Classifier: Environment :: Web Environment
Classifier: Framework :: Django
Classifier: Framework :: Django :: 4.0
Classifier: Framework :: Django :: 4.1
Classifier: Framework :: Django :: 4.2
Classifier: Intended Audience :: Developers
Classifier: License :: OSI Approved :: Apache Software License
Classifier: Operating System :: OS Independent
Classifier: Programming Language :: Python
Classifier: Programming Language :: Python :: 3
Classifier: Programming Language :: Python :: 3 :: Only
Classifier: Programming Language :: Python :: 3.10
Classifier: Programming Language :: Python :: 3.11
Classifier: Topic :: Internet :: WWW/HTTP
Classifier: Topic :: Internet :: WWW/HTTP :: Dynamic Content
Classifier: Topic :: Internet :: WWW/HTTP :: Dynamic Content :: Content Management System
Requires-Python: >=3.10
License-File: LICENSE
Requires-Dist: django (>=4.0)
Requires-Dist: pillow (>=9.4.0)
Provides-Extra: dev
Requires-Dist: python-lsp-server[autopep8,mccabe,pycodestyle,pyflakes,rope] ; extra == 'dev'
Requires-Dist: pylsp-rope ; extra == 'dev'
Provides-Extra: graphql
Requires-Dist: ariadne (>=0.16.0) ; extra == 'graphql'
Requires-Dist: ariadne-relay (>=0.1.0a8) ; extra == 'graphql'
Provides-Extra: test
Requires-Dist: pytest ; extra == 'test'
Requires-Dist: pytest-cov ; extra == 'test'
Requires-Dist: pytest-mock ; extra == 'test'
Requires-Dist: pytest-django ; extra == 'test'
